docs/source/conf.py
examples/download.py
examples/example.py
nexradaws/__init__.py
nexradaws/nexradawsinterface.py
nexradaws/resources/__init__.py
nexradaws/resources/awsnexradfile.py
nexradaws/resources/downloadresults.py
nexradaws/resources/localnexradfile.py
tests/__init__.py
tests/test_downloadResults.py
tests/test_nexradAwsFile.py
tests/test_nexradAwsInterface.py
nexradaws-2.0.0.dist-info/LICENSE
nexradaws-2.0.0.dist-info/METADATA
nexradaws-2.0.0.dist-info/WHEEL
nexradaws-2.0.0.dist-info/top_level.txt
nexradaws-2.0.0.dist-info/RECORD
