Metadata-Version: 2.2
Name: nexradaws
Version: 2.0.0
Summary: Query and download NEXRAD data from AWS S3 storage.
Author: Aaron Anderson
License: MIT
Project-URL: Homepage, https://nexradaws.readthedocs.io/en/latest/
Project-URL: Documentation, https://nexradaws.readthedocs.io/en/latest/
Project-URL: Repository, https://github.com/aarande/nexradaws
Project-URL: Issues, https://github.com/aarande/nexradaws/issues
Keywords: weather,radar,nexrad,aws,amazon
Classifier: Development Status :: 5 - Production/Stable
Classifier: Intended Audience :: Science/Research
Classifier: Topic :: Scientific/Engineering :: Atmospheric Science
Classifier: Programming Language :: Python :: 3
Classifier: Programming Language :: Python :: 3 :: Only
Classifier: Programming Language :: Python :: 3.8
Classifier: Programming Language :: Python :: 3.9
Classifier: Programming Language :: Python :: 3.10
Classifier: Programming Language :: Python :: 3.11
Classifier: Programming Language :: Python :: 3.12
Requires-Python: >=3.8
License-File: LICENSE
Requires-Dist: boto3
Requires-Dist: pytz
Provides-Extra: pyart
Requires-Dist: arm_pyart; extra == "pyart"
